{"card_name": "Blessing of Morning", "color": "W", "rarity": "rare", "type": "Enchantment", "number": 6, "color_identity": "W", "cost": "{5}{W}", "rules_text": "At the beginning of your upkeep, create two 1/1 colorless Construct artifact creature tokens, then you gain life equal to the number of artifacts and enchantments you control.", "flavor_text": "[i]\u201cLady Mari gifted me this power, and pointed me in the direction of planes that need help. If it takes an army to destroy the Banished, I will make one.\u201d\n\u2014Alia, Bearer of Morning[/i]", "pt": "", "special_text": "", "shape": "normal", "set": "DOA", "loyalty": "", "artist": "Lisa Buijteweg", "notes": "!changed", "image_type": "jpg"}