{"card_name": "Destructive Ambition", "color": "UB", "rarity": "common", "type": "Instant", "number": 198, "color_identity": "UB", "cost": "{U}{B}", "rules_text": "Counter target monocolored spell. Its controller loses 2 life.", "flavor_text": "[i]\u201cThe sky is our birthright; it is only human to wish to claim it.\u201d\n\u2014President Myers, Mission Statement[/i]", "pt": "", "special_text": "", "shape": "normal", "set": "LVS", "loyalty": "", "artist": "Lennart Demes", "notes": "Panacea for the Poison \u2014 Flobots\n!done", "image_type": "jpg"}