{"card_name": "Daisy, the Heart of Chasmek", "color": "G", "rarity": "rare", "type": "Legendary Creature \u2013 Human", "number": 83, "color_identity": "G", "cost": "{G}", "rules_text": "Other creatures you control get +1/+1 as long as you control four or more lands.\n{G}, Sacrifice Daisy, the Heart of Chasmek: Creatures you control with base power 1 or less gain indestructible until end of turn.", "flavor_text": "[i]\u201cSo much depends on a young girl, bright and hopeful, and her rabbit.\u201d\n\u2014Azamir, \u201cThe Trials of Chasmek\u201d[/i]", "pt": "1/1", "special_text": "", "shape": "normal", "set": "101", "loyalty": "", "artist": "Mansik Yang", "notes": "fluffy: swapped order on first ability (weapons trainer), -dashgap\nFluffy's Favourite Green Card", "image_type": "jpg"}