{"card_name": "Eltensian Hospitality", "color": "R", "rarity": "mythic", "type": "Enchantment", "number": 133, "color_identity": "R", "cost": "{2}{R}{R}", "rules_text": "{R}, Discard a land card: Eltensian Hospitality deals 3 damage to any target.\nWhenever you cast an instant or sorcery spell while you're ancient, copy that spell. You may choose new targets for the copy. [i](You're ancient as long as you have eight or more total lands in play or in your graveyard.)[/i]", "flavor_text": "[i]Scratch's return turned the world itself against undeath.[/i]", "pt": "", "special_text": "", "shape": "normal", "set": "BLR", "loyalty": "", "artist": "Michal Kvac", "notes": "", "image_type": "jpg"}