{"card_name": "Sylph of the Tugae", "color": "W", "rarity": "common", "type": "Creature \u2013 Elemental", "number": 37, "color_identity": "W", "cost": "{2}{W}", "rules_text": "Multitude {5}{W} [i](You may cast this for {5}{W}. When you do, copy it.)[/i]\nVigilance", "flavor_text": "[i]As Kywon's ambitions have grown, so has the Wildcourt's hatred of him.[/i]", "pt": "3/2", "special_text": "", "shape": "normal", "set": "BLR", "loyalty": "", "artist": "Tingyu C", "notes": "", "image_type": "jpg"}