{"card_name": "Exhausted Explorer", "color": "G", "rarity": "uncommon", "type": "Creature \u2013 Human Scout", "number": 167, "color_identity": "G", "cost": "{2}{G}", "rules_text": "Vigilance\n{G}, {T}: Exile up to three target cards from graveyards. If two or more of those cards share a card type, create a 1/1 colorless Servo artifact creature token.", "flavor_text": "[i]\u201cHere we go, for the hundredth time.\u201d[/i]", "pt": "2/3", "special_text": "", "shape": "normal", "set": "AVX", "loyalty": "", "artist": "Ken Fairclough", "notes": "Bleed It Out \u2014 Linkin Park", "image_type": "jpg"}